cracker_say
