Metadata-Version: 2.1
Name: cracker-saying
Version: 3.2
Summary: A simple pip for designing & designing termux banner.
Home-page: https://pypi.org/project/cracker-saying
Download-URL: https://pypi.org/project/cracker-saying
Author: cracker911181
Author-email: admin@cracker911181.cf
License: MIT
License-File: LICENSE
